infrash_embedded/__init__.py
infrash_embedded/_version.py
infrash_embedded/analyzer.py
infrash_embedded/cli.py
infrash_embedded-0.1.23.dist-info/licenses/LICENSE
infrash_embedded-0.1.23.dist-info/METADATA
infrash_embedded-0.1.23.dist-info/WHEEL
infrash_embedded-0.1.23.dist-info/entry_points.txt
infrash_embedded-0.1.23.dist-info/top_level.txt
infrash_embedded-0.1.23.dist-info/RECORD
