Metadata-Version: 2.4
Name: infrash_embedded
Version: 0.1.23
Summary: Energy optimization tool for embedded systems, particularly MSP430 microcontrollers
Home-page: https://github.com/infrash_embedded/infrash_embedded
Author: Tom Softreck
Author-email: info@softreck.dev
License: Apache License 2.0
Classifier: Programming Language :: Python :: 3
Classifier: License :: OSI Approved :: Apache Software License
Classifier: Operating System :: OS Independent
Classifier: Development Status :: 3 - Alpha
Classifier: Intended Audience :: Developers
Classifier: Topic :: Software Development :: Embedded Systems
Classifier: Topic :: Software Development :: Quality Assurance
Requires-Python: >=3.7
License-File: LICENSE
Requires-Dist: colorama>=0.4.4
Requires-Dist: click>=8.0.0
Requires-Dist: pycparser>=2.21
Requires-Dist: pytest>=7.0.0
Requires-Dist: pytest-cov>=3.0.0
Requires-Dist: pylint>=2.12.0
Requires-Dist: typing-extensions>=4.0.0
Dynamic: author
Dynamic: author-email
Dynamic: classifier
Dynamic: description
Dynamic: description-content-type
Dynamic: home-page
Dynamic: license-file
Dynamic: requires-dist
Dynamic: requires-python
Dynamic: summary
